[
  {
    "__type__": "cc.SpriteFrame",
    "content": {
      "name": "default_toggle_normal",
      "texture": "d2kHe6FidKcpV5e1aiNTQM",
      "rect": [
        0,
        0,
        28,
        28
      ],
      "offset": [
        0,
        0
      ],
      "originalSize": [
        28,
        28
      ],
      "capInsets": [
        0,
        0,
        0,
        0
      ]
    }
  },
  {
    "__type__": "cc.SpriteFrame",
    "content": {
      "name": "default_toggle_checkmark",
      "texture": "73oJA92A5OPKpn+ZlUPAj1",
      "rect": [
        4,
        5,
        20,
        18
      ],
      "offset": [
        0,
        0
      ],
      "originalSize": [
        28,
        28
      ],
      "capInsets": [
        0,
        0,
        0,
        0
      ]
    }
  },
  [
    {
      "__type__": "cc.Prefab",
      "_name": "toggle",
      "data": {
        "__id__": 1
      }
    },
    {
      "__type__": "cc.Node",
      "_name": "toggle",
      "_children": [
        {
          "__id__": 2
        },
        {
          "__id__": 3
        },
        {
          "__id__": 5
        }
      ],
      "_components": [
        {
          "__type__": "cc.Toggle",
          "node": {
            "__id__": 1
          },
          "_N$transition": 3,
          "transition": 3,
          "_N$normalColor": {
            "__type__": "cc.Color",
            "r": 214,
            "g": 214,
            "b": 214
          },
          "_N$target": {
            "__id__": 2
          },
          "checkMark": {
            "__id__": 4
          }
        }
      ],
      "_prefab": {
        "__type__": "cc.PrefabInfo",
        "root": {
          "__id__": 1
        },
        "asset": {
          "__id__": 0
        },
        "fileId": "f1x72jXPxBhZbAUUlxQwv4"
      },
      "_contentSize": {
        "__type__": "cc.Size",
        "width": 50,
        "height": 50
      },
      "_trs": {
        "__type__": "TypedArray",
        "ctor": "Float64Array",
        "array": [
          27.495,
          -96.837,
          0,
          0,
          0,
          0,
          1,
          1,
          1,
          1
        ]
      }
    },
    {
      "__type__": "cc.Node",
      "_name": "Background",
      "_objFlags": 512,
      "_parent": {
        "__id__": 1
      },
      "_components": [
        {
          "__type__": "cc.Sprite",
          "node": {
            "__id__": 2
          },
          "_materials": [
            {
              "__uuid__": "ecpdLyjvZBwrvm+cedCcQy"
            }
          ],
          "_spriteFrame": {
            "__uuid__": "68J8oyAQdFUrqy37MXmbtE"
          },
          "_sizeMode": 0
        }
      ],
      "_prefab": {
        "__type__": "cc.PrefabInfo",
        "root": {
          "__id__": 1
        },
        "asset": {
          "__id__": 0
        },
        "fileId": "300WMvNglKz4G+J0jUG1c2"
      },
      "_contentSize": {
        "__type__": "cc.Size",
        "width": 50,
        "height": 50
      },
      "_trs": {
        "__type__": "TypedArray",
        "ctor": "Float64Array",
        "array": [
          0,
          0,
          0,
          0,
          0,
          0,
          1,
          1,
          1,
          1
        ]
      }
    },
    {
      "__type__": "cc.Node",
      "_name": "checkmark",
      "_objFlags": 512,
      "_parent": {
        "__id__": 1
      },
      "_components": [
        {
          "__id__": 4
        }
      ],
      "_prefab": {
        "__type__": "cc.PrefabInfo",
        "root": {
          "__id__": 1
        },
        "asset": {
          "__id__": 0
        },
        "fileId": "32KBP9rr5CKrQTGWozG7tL"
      },
      "_contentSize": {
        "__type__": "cc.Size",
        "width": 50,
        "height": 50
      },
      "_trs": {
        "__type__": "TypedArray",
        "ctor": "Float64Array",
        "array": [
          0,
          0,
          0,
          0,
          0,
          0,
          1,
          1,
          1,
          1
        ]
      }
    },
    {
      "__type__": "cc.Sprite",
      "node": {
        "__id__": 3
      },
      "_materials": [
        {
          "__uuid__": "ecpdLyjvZBwrvm+cedCcQy"
        }
      ],
      "_spriteFrame": {
        "__uuid__": "90AErWL21A4ZPvtxQ3XG8G"
      },
      "_sizeMode": 0,
      "_isTrimmedMode": false
    },
    {
      "__type__": "cc.Node",
      "_name": "card",
      "_parent": {
        "__id__": 1
      },
      "_components": [
        {
          "__type__": "cc.Label",
          "node": {
            "__id__": 5
          },
          "_materials": [
            {
              "__uuid__": "ecpdLyjvZBwrvm+cedCcQy"
            }
          ],
          "_useOriginalSize": false,
          "_string": "平民",
          "_N$string": "平民",
          "_N$horizontalAlign": 1,
          "_N$verticalAlign": 1
        }
      ],
      "_prefab": {
        "__type__": "cc.PrefabInfo",
        "root": {
          "__id__": 1
        },
        "asset": {
          "__id__": 0
        },
        "fileId": "a9PNr88cRPnroRBBUGN2by"
      },
      "_color": {
        "__type__": "cc.Color"
      },
      "_contentSize": {
        "__type__": "cc.Size",
        "width": 80,
        "height": 50.4
      },
      "_anchorPoint": {
        "__type__": "cc.Vec2",
        "y": 0.5
      },
      "_trs": {
        "__type__": "TypedArray",
        "ctor": "Float64Array",
        "array": [
          40,
          0,
          0,
          0,
          0,
          0,
          1,
          1,
          1,
          1
        ]
      }
    }
  ]
]